LICENSE
README.md
setup.cfg
setup.py
cleaner_panda/__init__.py
cleaner_panda/categorical_encoder.py
cleaner_panda/data_type_converter.py
cleaner_panda/date_time_handler.py
cleaner_panda/missing_value_handler.py
cleaner_panda/outlier_handler.py
cleaner_panda/scaler.py
cleaner_panda/text_cleaner.py
cleaner_panda.egg-info/PKG-INFO
cleaner_panda.egg-info/SOURCES.txt
cleaner_panda.egg-info/dependency_links.txt
cleaner_panda.egg-info/requires.txt
cleaner_panda.egg-info/top_level.txt
tests/__init__.py
tests/test_categorical_encoder.py
tests/test_data_type_converter.py
tests/test_date_time_handler.py
tests/test_missing_value_handler.py
tests/test_outlier_handler.py
tests/test_scaler.py
tests/test_text_cleaner.py